gooddata_flexfun/__init__.py
gooddata_flexfun/flexfun/__init__.py
gooddata_flexfun/flexfun/flex_fun.py
gooddata_flexfun/flexfun/flex_fun_execution_context.py
gooddata_flexfun/flexfun/flex_fun_registry.py
gooddata_flexfun/flexfun/flex_fun_task.py
gooddata_flexfun/flexfun/flight_methods.py
gooddata_flexfun-1.30.0.dist-info/LICENSE.txt
gooddata_flexfun-1.30.0.dist-info/METADATA
gooddata_flexfun-1.30.0.dist-info/WHEEL
gooddata_flexfun-1.30.0.dist-info/top_level.txt
gooddata_flexfun-1.30.0.dist-info/RECORD
