Metadata-Version: 2.1
Name: gooddata-flexfun
Version: 1.30.0
Summary: Set of gooddata-flight-server methods to host custom functions for GoodData Cloud
Author: GoodData
Author-email: support@gooddata.com
License: MIT
Project-URL: Documentation, https://gooddata-flexfun.readthedocs.io/en/v1.30.0
Project-URL: Source, https://github.com/gooddata/gooddata-python-sdk
Keywords: gooddata,flight,rpc,flight rpc,custom functions,analytics,headless,business,intelligence,headless-bi,cloud,native,semantic,layer,sql,metrics
Classifier: Development Status :: 4 - Beta
Classifier: Environment :: Console
Classifier: License :: OSI Approved :: MIT License
Classifier: Programming Language :: Python :: 3.9
Classifier: Programming Language :: Python :: 3.10
Classifier: Programming Language :: Python :: 3.11
Classifier: Programming Language :: Python :: 3.12
Classifier: Topic :: Database
Classifier: Topic :: Scientific/Engineering
Classifier: Topic :: Software Development
Classifier: Typing :: Typed
Requires-Python: >=3.9.0
License-File: LICENSE.txt
Requires-Dist: dynaconf <4.0.0,>=3.1.11
Requires-Dist: gooddata-flight-server ~=1.30.0
Requires-Dist: gooddata-sdk ~=1.30.0
Requires-Dist: orjson <4.0.0,>=3.9.15
Requires-Dist: pyarrow >=16.1.0
Requires-Dist: structlog <25.0.0,>=24.0.0
